i2b2_import/data_catalog_import.py
i2b2_import/clm_extension.py
i2b2_import/ppmi_extension.py
i2b2_import/utils.py
i2b2_import/edsd_extension.py
i2b2_import/__init__.py
i2b2_import/data_catalog_connection.py
i2b2_import/features_csv_import.py
i2b2_import/meta_files_import.py
i2b2_import/i2b2_connection.py
i2b2_import/default_data/default_structures_mapping.csv
i2b2_import-1.6.3.dist-info/top_level.txt
i2b2_import-1.6.3.dist-info/METADATA
i2b2_import-1.6.3.dist-info/DESCRIPTION.rst
i2b2_import-1.6.3.dist-info/metadata.json
i2b2_import-1.6.3.dist-info/WHEEL
i2b2_import-1.6.3.dist-info/RECORD
