Metadata-Version: 2.0
Name: i2b2-import
Version: 1.6.3
Summary: Import data into an I2B2 DB schema
Home-page: https://github.com/LREN-CHUV/i2b2-import
Author: Mirco Nasuti
Author-email: mirco.nasuti@chuv.ch
License: Apache 2.0
Platform: UNKNOWN
Classifier: Intended Audience :: Developers
Classifier: Intended Audience :: Science/Research
Classifier: Operating System :: Unix
Classifier: License :: OSI Approved :: Apache Software License
Classifier: Topic :: Scientific/Engineering :: Bio-Informatics
Classifier: Programming Language :: Python :: 3 :: Only
Classifier: Programming Language :: Python :: 3.4
Classifier: Programming Language :: Python :: 3.5
Classifier: Programming Language :: Python :: 3.6
Requires-Dist: apache-airflow (>=1.8.1)
Requires-Dist: SQLAlchemy (>=1.1.6)
Requires-Dist: psycopg2 (>=2.7.1)
Requires-Dist: pandas
Requires-Dist: defusedxml
Requires-Dist: xlrd
Provides-Extra: test
Requires-Dist: unittest; extra == 'test'
Requires-Dist: nose; extra == 'test'
